{
  "data": {
    "average": 1592,
    "bid": [
      {
        "price": "1580",
        "que_num": "19",
        "volume": "50400",
        "change_percentage": ""
      },
      {
        "price": "1575",
        "que_num": "6",
        "volume": "3000",
        "change_percentage": ""
      },
      {
        "price": "1570",
        "que_num": "11",
        "volume": "57400",
        "change_percentage": ""
      },
      {
        "price": "1565",
        "que_num": "8",
        "volume": "11400",
        "change_percentage": ""
      },
      {
        "price": "1560",
        "que_num": "8",
        "volume": "63200",
        "change_percentage": ""
      },
      {
        "price": "1555",
        "que_num": "5",
        "volume": "3900",
        "change_percentage": ""
      },
      {
        "price": "1550",
        "que_num": "5",
        "volume": "56800",
        "change_percentage": ""
      },
      {
        "price": "1540",
        "que_num": "7",
        "volume": "56800",
        "change_percentage": ""
      },
      {
        "price": "1535",
        "que_num": "53",
        "volume": "133400",
        "change_percentage": ""
      },
      {
        "price": "1530",
        "que_num": "25",
        "volume": "80200",
        "change_percentage": ""
      },
      {
        "price": "1525",
        "que_num": "2",
        "volume": "5200",
        "change_percentage": ""
      },
      {
        "price": "1520",
        "que_num": "9",
        "volume": "56200",
        "change_percentage": ""
      },
      {
        "price": "1515",
        "que_num": "4",
        "volume": "21200",
        "change_percentage": ""
      },
      {
        "price": "1510",
        "que_num": "11",
        "volume": "136000",
        "change_percentage": ""
      },
      {
        "price": "1505",
        "que_num": "8",
        "volume": "23400",
        "change_percentage": ""
      },
      {
        "price": "1500",
        "que_num": "10",
        "volume": "53400",
        "change_percentage": ""
      },
      {
        "price": "1495",
        "que_num": "2",
        "volume": "1100",
        "change_percentage": ""
      },
      {
        "price": "1490",
        "que_num": "3",
        "volume": "10400",
        "change_percentage": ""
      },
      {
        "price": "1485",
        "que_num": "1",
        "volume": "100",
        "change_percentage": ""
      },
      {
        "price": "1480",
        "que_num": "6",
        "volume": "70600",
        "change_percentage": ""
      },
      {
        "price": "1475",
        "que_num": "2",
        "volume": "3200",
        "change_percentage": ""
      },
      {
        "price": "1470",
        "que_num": "1",
        "volume": "100",
        "change_percentage": ""
      },
      {
        "price": "1465",
        "que_num": "1",
        "volume": "500",
        "change_percentage": ""
      },
      {
        "price": "1460",
        "que_num": "1",
        "volume": "100",
        "change_percentage": ""
      },
      {
        "price": "1455",
        "que_num": "1",
        "volume": "700",
        "change_percentage": ""
      },
      {
        "price": "1450",
        "que_num": "4",
        "volume": "1400",
        "change_percentage": ""
      },
      {
        "price": "1440",
        "que_num": "1",
        "volume": "100",
        "change_percentage": ""
      },
      {
        "price": "1435",
        "que_num": "3",
        "volume": "25700",
        "change_percentage": ""
      },
      {
        "price": "1430",
        "que_num": "3",
        "volume": "1200",
        "change_percentage": ""
      },
      {
        "price": "1420",
        "que_num": "2",
        "volume": "5100",
        "change_percentage": ""
      },
      {
        "price": "1415",
        "que_num": "2",
        "volume": "3000",
        "change_percentage": ""
      },
      {
        "price": "1410",
        "que_num": "1",
        "volume": "100",
        "change_percentage": ""
      },
      {
        "price": "1405",
        "que_num": "1",
        "volume": "100",
        "change_percentage": ""
      },
      {
        "price": "1400",
        "que_num": "5",
        "volume": "4300",
        "change_percentage": ""
      },
      {
        "price": "1390",
        "que_num": "3",
        "volume": "3100",
        "change_percentage": ""
      },
      {
        "price": "1380",
        "que_num": "2",
        "volume": "2100",
        "change_percentage": ""
      },
      {
        "price": "1370",
        "que_num": "2",
        "volume": "2600",
        "change_percentage": ""
      },
      {
        "price": "1360",
        "que_num": "1",
        "volume": "100",
        "change_percentage": ""
      },
      {
        "price": "1355",
        "que_num": "1",
        "volume": "1000",
        "change_percentage": ""
      },
      {
        "price": "1350",
        "que_num": "1",
        "volume": "100",
        "change_percentage": ""
      },
      {
        "price": "1345",
        "que_num": "3",
        "volume": "3500",
        "change_percentage": ""
      }
    ],
    "change": 5,
    "close": 1585,
    "country": "ID",
    "domestic": "100.00",
    "down": "110",
    "exchange": "IDX",
    "fbuy": 551874000,
    "fnet": -887345000,
    "foreign": "0.00",
    "frequency": 322,
    "fsell": 1439219000,
    "high": 1605,
    "id": "WIIM-0",
    "lastprice": 1585,
    "low": 1580,
    "offer": [
      {
        "price": "1585",
        "que_num": "5",
        "volume": "74900",
        "change_percentage": ""
      },
      {
        "price": "1590",
        "que_num": "7",
        "volume": "9500",
        "change_percentage": ""
      },
      {
        "price": "1595",
        "que_num": "14",
        "volume": "31100",
        "change_percentage": ""
      },
      {
        "price": "1600",
        "que_num": "17",
        "volume": "167400",
        "change_percentage": ""
      },
      {
        "price": "1605",
        "que_num": "9",
        "volume": "37000",
        "change_percentage": ""
      },
      {
        "price": "1610",
        "que_num": "4",
        "volume": "7000",
        "change_percentage": ""
      },
      {
        "price": "1615",
        "que_num": "12",
        "volume": "86300",
        "change_percentage": ""
      },
      {
        "price": "1620",
        "que_num": "8",
        "volume": "33800",
        "change_percentage": ""
      },
      {
        "price": "1625",
        "que_num": "5",
        "volume": "71300",
        "change_percentage": ""
      },
      {
        "price": "1630",
        "que_num": "7",
        "volume": "4400",
        "change_percentage": ""
      },
      {
        "price": "1635",
        "que_num": "5",
        "volume": "73300",
        "change_percentage": ""
      },
      {
        "price": "1640",
        "que_num": "8",
        "volume": "38200",
        "change_percentage": ""
      },
      {
        "price": "1645",
        "que_num": "9",
        "volume": "58800",
        "change_percentage": ""
      },
      {
        "price": "1650",
        "que_num": "12",
        "volume": "38400",
        "change_percentage": ""
      },
      {
        "price": "1655",
        "que_num": "4",
        "volume": "60200",
        "change_percentage": ""
      },
      {
        "price": "1660",
        "que_num": "5",
        "volume": "5000",
        "change_percentage": ""
      },
      {
        "price": "1665",
        "que_num": "3",
        "volume": "10800",
        "change_percentage": ""
      },
      {
        "price": "1670",
        "que_num": "7",
        "volume": "34800",
        "change_percentage": ""
      },
      {
        "price": "1675",
        "que_num": "4",
        "volume": "16000",
        "change_percentage": ""
      },
      {
        "price": "1680",
        "que_num": "4",
        "volume": "8500",
        "change_percentage": ""
      },
      {
        "price": "1685",
        "que_num": "2",
        "volume": "300",
        "change_percentage": ""
      },
      {
        "price": "1690",
        "que_num": "7",
        "volume": "16400",
        "change_percentage": ""
      },
      {
        "price": "1695",
        "que_num": "3",
        "volume": "5600",
        "change_percentage": ""
      },
      {
        "price": "1700",
        "que_num": "11",
        "volume": "16100",
        "change_percentage": ""
      },
      {
        "price": "1705",
        "que_num": "2",
        "volume": "700",
        "change_percentage": ""
      },
      {
        "price": "1710",
        "que_num": "6",
        "volume": "56000",
        "change_percentage": ""
      },
      {
        "price": "1715",
        "que_num": "1",
        "volume": "100",
        "change_percentage": ""
      },
      {
        "price": "1720",
        "que_num": "5",
        "volume": "12700",
        "change_percentage": ""
      },
      {
        "price": "1725",
        "que_num": "2",
        "volume": "200",
        "change_percentage": ""
      },
      {
        "price": "1730",
        "que_num": "6",
        "volume": "124700",
        "change_percentage": ""
      },
      {
        "price": "1735",
        "que_num": "1",
        "volume": "100",
        "change_percentage": ""
      },
      {
        "price": "1740",
        "que_num": "4",
        "volume": "1200",
        "change_percentage": ""
      },
      {
        "price": "1745",
        "que_num": "2",
        "volume": "25100",
        "change_percentage": ""
      },
      {
        "price": "1750",
        "que_num": "8",
        "volume": "183700",
        "change_percentage": ""
      },
      {
        "price": "1755",
        "que_num": "4",
        "volume": "4600",
        "change_percentage": ""
      },
      {
        "price": "1760",
        "que_num": "6",
        "volume": "6700",
        "change_percentage": ""
      },
      {
        "price": "1765",
        "que_num": "4",
        "volume": "5500",
        "change_percentage": ""
      },
      {
        "price": "1770",
        "que_num": "12",
        "volume": "27100",
        "change_percentage": ""
      },
      {
        "price": "1775",
        "que_num": "2",
        "volume": "400",
        "change_percentage": ""
      },
      {
        "price": "1780",
        "que_num": "8",
        "volume": "30000",
        "change_percentage": ""
      },
      {
        "price": "1785",
        "que_num": "3",
        "volume": "5200",
        "change_percentage": ""
      },
      {
        "price": "1790",
        "que_num": "5",
        "volume": "13200",
        "change_percentage": ""
      },
      {
        "price": "1795",
        "que_num": "3",
        "volume": "2600",
        "change_percentage": ""
      },
      {
        "price": "1800",
        "que_num": "15",
        "volume": "30500",
        "change_percentage": ""
      },
      {
        "price": "1805",
        "que_num": "3",
        "volume": "5500",
        "change_percentage": ""
      },
      {
        "price": "1810",
        "que_num": "4",
        "volume": "2200",
        "change_percentage": ""
      },
      {
        "price": "1815",
        "que_num": "3",
        "volume": "5400",
        "change_percentage": ""
      },
      {
        "price": "1820",
        "que_num": "7",
        "volume": "6900",
        "change_percentage": ""
      },
      {
        "price": "1825",
        "que_num": "2",
        "volume": "1200",
        "change_percentage": ""
      },
      {
        "price": "1830",
        "que_num": "4",
        "volume": "2100",
        "change_percentage": ""
      },
      {
        "price": "1835",
        "que_num": "5",
        "volume": "24800",
        "change_percentage": ""
      },
      {
        "price": "1840",
        "que_num": "6",
        "volume": "7700",
        "change_percentage": ""
      },
      {
        "price": "1845",
        "que_num": "2",
        "volume": "1900",
        "change_percentage": ""
      },
      {
        "price": "1850",
        "que_num": "8",
        "volume": "11900",
        "change_percentage": ""
      },
      {
        "price": "1855",
        "que_num": "2",
        "volume": "2000",
        "change_percentage": ""
      },
      {
        "price": "1860",
        "que_num": "6",
        "volume": "10100",
        "change_percentage": ""
      },
      {
        "price": "1865",
        "que_num": "3",
        "volume": "2300",
        "change_percentage": ""
      },
      {
        "price": "1870",
        "que_num": "3",
        "volume": "4100",
        "change_percentage": ""
      },
      {
        "price": "1875",
        "que_num": "2",
        "volume": "2000",
        "change_percentage": ""
      },
      {
        "price": "1880",
        "que_num": "5",
        "volume": "46600",
        "change_percentage": ""
      },
      {
        "price": "1885",
        "que_num": "2",
        "volume": "2000",
        "change_percentage": ""
      },
      {
        "price": "1890",
        "que_num": "3",
        "volume": "3600",
        "change_percentage": ""
      },
      {
        "price": "1895",
        "que_num": "5",
        "volume": "5100",
        "change_percentage": ""
      },
      {
        "price": "1900",
        "que_num": "10",
        "volume": "339900",
        "change_percentage": ""
      },
      {
        "price": "1905",
        "que_num": "3",
        "volume": "4500",
        "change_percentage": ""
      },
      {
        "price": "1910",
        "que_num": "5",
        "volume": "15700",
        "change_percentage": ""
      },
      {
        "price": "1915",
        "que_num": "5",
        "volume": "6000",
        "change_percentage": ""
      },
      {
        "price": "1920",
        "que_num": "4",
        "volume": "7100",
        "change_percentage": ""
      },
      {
        "price": "1925",
        "que_num": "4",
        "volume": "2600",
        "change_percentage": ""
      },
      {
        "price": "1930",
        "que_num": "5",
        "volume": "1800",
        "change_percentage": ""
      },
      {
        "price": "1935",
        "que_num": "3",
        "volume": "2300",
        "change_percentage": ""
      },
      {
        "price": "1945",
        "que_num": "3",
        "volume": "7300",
        "change_percentage": ""
      },
      {
        "price": "1950",
        "que_num": "4",
        "volume": "23000",
        "change_percentage": ""
      },
      {
        "price": "1955",
        "que_num": "5",
        "volume": "74500",
        "change_percentage": ""
      },
      {
        "price": "1965",
        "que_num": "2",
        "volume": "2300",
        "change_percentage": ""
      },
      {
        "price": "1970",
        "que_num": "1",
        "volume": "1500",
        "change_percentage": ""
      },
      {
        "price": "1975",
        "que_num": "15",
        "volume": "222500",
        "change_percentage": ""
      }
    ],
    "open": 1585,
    "percentage_change": 0.32,
    "previous": 1580,
    "status": "Active",
    "symbol": "WIIM",
    "symbol_2": "WIIM",
    "symbol_3": "WIIM",
    "tradable": true,
    "unchanged": "1118",
    "up": "265",
    "value": 956444000,
    "volume": 600700,
    "corp_action": {
      "active": false,
      "icon": "https://assets.stockbit.com/images/corp_action_event_icon.svg",
      "text": "Perusahaan Memiliki Corporate Action"
    },
    "notation": [],
    "uma": false,
    "has_foreign_bs": false,
    "iepiev": {
      "symbol": "",
      "status": "STATUS_UNSPECIFIED",
      "iep": {
        "raw": 0,
        "formatted": ""
      },
      "iev": {
        "raw": 0,
        "formatted": ""
      },
      "time_left_seconds": 0,
      "best_bid_offer": null,
      "title": "",
      "iep_changes": {
        "price": {
          "raw": 0,
          "formatted": ""
        },
        "percentage": {
          "raw": 0,
          "formatted": ""
        }
      }
    },
    "market_data": [
      {
        "label": "All Market",
        "frequency": {
          "raw": "322",
          "formatted": "322"
        },
        "volume": {
          "raw": "600700",
          "formatted": "601 K"
        },
        "value": {
          "raw": "956444000",
          "formatted": "956 M"
        }
      },
      {
        "label": "Regular",
        "frequency": {
          "raw": "322",
          "formatted": "322"
        },
        "volume": {
          "raw": "600700",
          "formatted": "601 K"
        },
        "value": {
          "raw": "956444000",
          "formatted": "956 M"
        }
      },
      {
        "label": "Nego",
        "frequency": {
          "raw": "0",
          "formatted": "0"
        },
        "volume": {
          "raw": "0",
          "formatted": "0"
        },
        "value": {
          "raw": "0",
          "formatted": "0"
        }
      },
      {
        "label": "Cash",
        "frequency": {
          "raw": "0",
          "formatted": "0"
        },
        "volume": {
          "raw": "0",
          "formatted": "0"
        },
        "value": {
          "raw": "0",
          "formatted": "0"
        }
      }
    ],
    "name": "PT Wismilak Inti Makmur Tbk.",
    "icon_url": "https://assets.stockbit.com/logos/companies/WIIM.png",
    "ara": {
      "value": "1,975",
      "visible": true
    },
    "arb": {
      "value": "1,345",
      "visible": true
    },
    "company_type": "Saham",
    "total_bid_offer": {
      "bid": {
        "freq": "244",
        "lot": "952,200"
      },
      "offer": {
        "freq": "415",
        "lot": "2,293,800"
      }
    },
    "next_ara": {
      "value": "1,975",
      "visible": true
    },
    "next_arb": {
      "value": "1,345",
      "visible": true
    },
    "autoreject_time_left_in_sec": 0,
    "auto_reject_estimation": [
      {
        "value": 189200,
        "change_to_prev": {
          "value": 31525,
          "percentage": 19.99
        },
        "change_to_base": {
          "value": 187620,
          "percentage": 11874.68
        },
        "type": "AUTO_REJECT_TYPE_POSITIVE"
      },
      {
        "value": 157675,
        "change_to_prev": {
          "value": 26275,
          "percentage": 20
        },
        "change_to_base": {
          "value": 156095,
          "percentage": 9879.43
        },
        "type": "AUTO_REJECT_TYPE_POSITIVE"
      },
      {
        "value": 131400,
        "change_to_prev": {
          "value": 21900,
          "percentage": 20
        },
        "change_to_base": {
          "value": 129820,
          "percentage": 8216.46
        },
        "type": "AUTO_REJECT_TYPE_POSITIVE"
      },
      {
        "value": 109500,
        "change_to_prev": {
          "value": 18250,
          "percentage": 20
        },
        "change_to_base": {
          "value": 107920,
          "percentage": 6830.38
        },
        "type": "AUTO_REJECT_TYPE_POSITIVE"
      },
      {
        "value": 91250,
        "change_to_prev": {
          "value": 15200,
          "percentage": 19.99
        },
        "change_to_base": {
          "value": 89670,
          "percentage": 5675.32
        },
        "type": "AUTO_REJECT_TYPE_POSITIVE"
      },
      {
        "value": 76050,
        "change_to_prev": {
          "value": 12675,
          "percentage": 20
        },
        "change_to_base": {
          "value": 74470,
          "percentage": 4713.29
        },
        "type": "AUTO_REJECT_TYPE_POSITIVE"
      },
      {
        "value": 63375,
        "change_to_prev": {
          "value": 10550,
          "percentage": 19.97
        },
        "change_to_base": {
          "value": 61795,
          "percentage": 3911.08
        },
        "type": "AUTO_REJECT_TYPE_POSITIVE"
      },
      {
        "value": 52825,
        "change_to_prev": {
          "value": 8800,
          "percentage": 19.99
        },
        "change_to_base": {
          "value": 51245,
          "percentage": 3243.35
        },
        "type": "AUTO_REJECT_TYPE_POSITIVE"
      },
      {
        "value": 44025,
        "change_to_prev": {
          "value": 7325,
          "percentage": 19.96
        },
        "change_to_base": {
          "value": 42445,
          "percentage": 2686.39
        },
        "type": "AUTO_REJECT_TYPE_POSITIVE"
      },
      {
        "value": 36700,
        "change_to_prev": {
          "value": 6100,
          "percentage": 19.93
        },
        "change_to_base": {
          "value": 35120,
          "percentage": 2222.78
        },
        "type": "AUTO_REJECT_TYPE_POSITIVE"
      },
      {
        "value": 30600,
        "change_to_prev": {
          "value": 5100,
          "percentage": 20
        },
        "change_to_base": {
          "value": 29020,
          "percentage": 1836.71
        },
        "type": "AUTO_REJECT_TYPE_POSITIVE"
      },
      {
        "value": 25500,
        "change_to_prev": {
          "value": 4250,
          "percentage": 20
        },
        "change_to_base": {
          "value": 23920,
          "percentage": 1513.92
        },
        "type": "AUTO_REJECT_TYPE_POSITIVE"
      },
      {
        "value": 21250,
        "change_to_prev": {
          "value": 3525,
          "percentage": 19.89
        },
        "change_to_base": {
          "value": 19670,
          "percentage": 1244.94
        },
        "type": "AUTO_REJECT_TYPE_POSITIVE"
      },
      {
        "value": 17725,
        "change_to_prev": {
          "value": 2950,
          "percentage": 19.97
        },
        "change_to_base": {
          "value": 16145,
          "percentage": 1021.84
        },
        "type": "AUTO_REJECT_TYPE_POSITIVE"
      },
      {
        "value": 14775,
        "change_to_prev": {
          "value": 2450,
          "percentage": 19.88
        },
        "change_to_base": {
          "value": 13195,
          "percentage": 835.13
        },
        "type": "AUTO_REJECT_TYPE_POSITIVE"
      },
      {
        "value": 12325,
        "change_to_prev": {
          "value": 2050,
          "percentage": 19.95
        },
        "change_to_base": {
          "value": 10745,
          "percentage": 680.06
        },
        "type": "AUTO_REJECT_TYPE_POSITIVE"
      },
      {
        "value": 10275,
        "change_to_prev": {
          "value": 1700,
          "percentage": 19.83
        },
        "change_to_base": {
          "value": 8695,
          "percentage": 550.32
        },
        "type": "AUTO_REJECT_TYPE_POSITIVE"
      },
      {
        "value": 8575,
        "change_to_prev": {
          "value": 1425,
          "percentage": 19.93
        },
        "change_to_base": {
          "value": 6995,
          "percentage": 442.72
        },
        "type": "AUTO_REJECT_TYPE_POSITIVE"
      },
      {
        "value": 7150,
        "change_to_prev": {
          "value": 1175,
          "percentage": 19.67
        },
        "change_to_base": {
          "value": 5570,
          "percentage": 352.53
        },
        "type": "AUTO_REJECT_TYPE_POSITIVE"
      },
      {
        "value": 5975,
        "change_to_prev": {
          "value": 1195,
          "percentage": 25
        },
        "change_to_base": {
          "value": 4395,
          "percentage": 278.16
        },
        "type": "AUTO_REJECT_TYPE_POSITIVE"
      },
      {
        "value": 4780,
        "change_to_prev": {
          "value": 950,
          "percentage": 24.8
        },
        "change_to_base": {
          "value": 3200,
          "percentage": 202.53
        },
        "type": "AUTO_REJECT_TYPE_POSITIVE"
      },
      {
        "value": 3830,
        "change_to_prev": {
          "value": 760,
          "percentage": 24.76
        },
        "change_to_base": {
          "value": 2250,
          "percentage": 142.41
        },
        "type": "AUTO_REJECT_TYPE_POSITIVE"
      },
      {
        "value": 3070,
        "change_to_prev": {
          "value": 610,
          "percentage": 24.8
        },
        "change_to_base": {
          "value": 1490,
          "percentage": 94.3
        },
        "type": "AUTO_REJECT_TYPE_POSITIVE"
      },
      {
        "value": 2460,
        "change_to_prev": {
          "value": 485,
          "percentage": 24.56
        },
        "change_to_base": {
          "value": 880,
          "percentage": 55.7
        },
        "type": "AUTO_REJECT_TYPE_POSITIVE"
      },
      {
        "value": 1975,
        "change_to_prev": {
          "value": 395,
          "percentage": 25
        },
        "change_to_base": {
          "value": 395,
          "percentage": 25
        },
        "type": "AUTO_REJECT_TYPE_POSITIVE"
      },
      {
        "value": 1580,
        "change_to_prev": {
          "value": 0,
          "percentage": 0
        },
        "change_to_base": {
          "value": 0,
          "percentage": 0
        },
        "type": "AUTO_REJECT_TYPE_BASE"
      },
      {
        "value": 1345,
        "change_to_prev": {
          "value": -235,
          "percentage": -14.87
        },
        "change_to_base": {
          "value": -235,
          "percentage": -14.87
        },
        "type": "AUTO_REJECT_TYPE_NEGATIVE"
      },
      {
        "value": 1145,
        "change_to_prev": {
          "value": -200,
          "percentage": -14.87
        },
        "change_to_base": {
          "value": -435,
          "percentage": -27.53
        },
        "type": "AUTO_REJECT_TYPE_NEGATIVE"
      },
      {
        "value": 975,
        "change_to_prev": {
          "value": -170,
          "percentage": -14.85
        },
        "change_to_base": {
          "value": -605,
          "percentage": -38.29
        },
        "type": "AUTO_REJECT_TYPE_NEGATIVE"
      },
      {
        "value": 830,
        "change_to_prev": {
          "value": -145,
          "percentage": -14.87
        },
        "change_to_base": {
          "value": -750,
          "percentage": -47.47
        },
        "type": "AUTO_REJECT_TYPE_NEGATIVE"
      },
      {
        "value": 710,
        "change_to_prev": {
          "value": -120,
          "percentage": -14.46
        },
        "change_to_base": {
          "value": -870,
          "percentage": -55.06
        },
        "type": "AUTO_REJECT_TYPE_NEGATIVE"
      },
      {
        "value": 605,
        "change_to_prev": {
          "value": -105,
          "percentage": -14.79
        },
        "change_to_base": {
          "value": -975,
          "percentage": -61.71
        },
        "type": "AUTO_REJECT_TYPE_NEGATIVE"
      },
      {
        "value": 515,
        "change_to_prev": {
          "value": -90,
          "percentage": -14.88
        },
        "change_to_base": {
          "value": -1065,
          "percentage": -67.41
        },
        "type": "AUTO_REJECT_TYPE_NEGATIVE"
      },
      {
        "value": 438,
        "change_to_prev": {
          "value": -77,
          "percentage": -14.95
        },
        "change_to_base": {
          "value": -1142,
          "percentage": -72.28
        },
        "type": "AUTO_REJECT_TYPE_NEGATIVE"
      },
      {
        "value": 374,
        "change_to_prev": {
          "value": -64,
          "percentage": -14.61
        },
        "change_to_base": {
          "value": -1206,
          "percentage": -76.33
        },
        "type": "AUTO_REJECT_TYPE_NEGATIVE"
      },
      {
        "value": 318,
        "change_to_prev": {
          "value": -56,
          "percentage": -14.97
        },
        "change_to_base": {
          "value": -1262,
          "percentage": -79.87
        },
        "type": "AUTO_REJECT_TYPE_NEGATIVE"
      },
      {
        "value": 272,
        "change_to_prev": {
          "value": -46,
          "percentage": -14.47
        },
        "change_to_base": {
          "value": -1308,
          "percentage": -82.78
        },
        "type": "AUTO_REJECT_TYPE_NEGATIVE"
      },
      {
        "value": 232,
        "change_to_prev": {
          "value": -40,
          "percentage": -14.71
        },
        "change_to_base": {
          "value": -1348,
          "percentage": -85.32
        },
        "type": "AUTO_REJECT_TYPE_NEGATIVE"
      },
      {
        "value": 198,
        "change_to_prev": {
          "value": -34,
          "percentage": -14.66
        },
        "change_to_base": {
          "value": -1382,
          "percentage": -87.47
        },
        "type": "AUTO_REJECT_TYPE_NEGATIVE"
      },
      {
        "value": 169,
        "change_to_prev": {
          "value": -29,
          "percentage": -14.65
        },
        "change_to_base": {
          "value": -1411,
          "percentage": -89.3
        },
        "type": "AUTO_REJECT_TYPE_NEGATIVE"
      },
      {
        "value": 144,
        "change_to_prev": {
          "value": -25,
          "percentage": -14.79
        },
        "change_to_base": {
          "value": -1436,
          "percentage": -90.89
        },
        "type": "AUTO_REJECT_TYPE_NEGATIVE"
      },
      {
        "value": 123,
        "change_to_prev": {
          "value": -21,
          "percentage": -14.58
        },
        "change_to_base": {
          "value": -1457,
          "percentage": -92.22
        },
        "type": "AUTO_REJECT_TYPE_NEGATIVE"
      },
      {
        "value": 105,
        "change_to_prev": {
          "value": -18,
          "percentage": -14.63
        },
        "change_to_base": {
          "value": -1475,
          "percentage": -93.35
        },
        "type": "AUTO_REJECT_TYPE_NEGATIVE"
      },
      {
        "value": 90,
        "change_to_prev": {
          "value": -15,
          "percentage": -14.29
        },
        "change_to_base": {
          "value": -1490,
          "percentage": -94.3
        },
        "type": "AUTO_REJECT_TYPE_NEGATIVE"
      },
      {
        "value": 77,
        "change_to_prev": {
          "value": -13,
          "percentage": -14.44
        },
        "change_to_base": {
          "value": -1503,
          "percentage": -95.13
        },
        "type": "AUTO_REJECT_TYPE_NEGATIVE"
      },
      {
        "value": 66,
        "change_to_prev": {
          "value": -11,
          "percentage": -14.29
        },
        "change_to_base": {
          "value": -1514,
          "percentage": -95.82
        },
        "type": "AUTO_REJECT_TYPE_NEGATIVE"
      },
      {
        "value": 57,
        "change_to_prev": {
          "value": -9,
          "percentage": -13.64
        },
        "change_to_base": {
          "value": -1523,
          "percentage": -96.39
        },
        "type": "AUTO_REJECT_TYPE_NEGATIVE"
      },
      {
        "value": 50,
        "change_to_prev": {
          "value": -7,
          "percentage": -12.28
        },
        "change_to_base": {
          "value": -1530,
          "percentage": -96.84
        },
        "type": "AUTO_REJECT_TYPE_NEGATIVE"
      }
    ],
    "orderbook_active_feature_mobile": "ORDER_BOOK_FEATURE_UNSPECIFIED"
  },
  "message": "Successfully get company orderbook"
}